clips.py
clips-1.1.0.dist-info/LICENSE
clips-1.1.0.dist-info/METADATA
clips-1.1.0.dist-info/WHEEL
clips-1.1.0.dist-info/top_level.txt
clips-1.1.0.dist-info/RECORD
