Metadata-Version: 2.1
Name: clips
Version: 1.1.0
Summary: Parser for command-line applications.
Home-page: https://github.com/acapitanelli/clips
Author: Andrea Capitanelli
Author-email: andrea@capitanelli.gmail.com
Maintainer: clips
Maintainer-email: andrea@capitanelli.gmail.com
License: MIT
Keywords: cli parser commands arguments colors
Platform: UNKNOWN
Classifier: Development Status :: 3 - Alpha
Classifier: License :: OSI Approved :: MIT License
Classifier: Programming Language :: Python :: 3
Classifier: Operating System :: POSIX :: Linux
Classifier: Topic :: Utilities
